python_kv/__init__.py
python_kv/cli.py
python_kv/client.py
python_kv/datastore.py
python_kv/kvstore.py
raft/go.mod
raft/go.sum
raft/raft.go
raft/raft_test.go
raft/server.go
raft/storage.go
raft/testharness.go
python_raft_kv-0.1.1.dist-info/METADATA
python_raft_kv-0.1.1.dist-info/WHEEL
python_raft_kv-0.1.1.dist-info/entry_points.txt
python_raft_kv-0.1.1.dist-info/top_level.txt
python_raft_kv-0.1.1.dist-info/RECORD
